{
  "lastUpdated": "2025-09-04T23:12:22.580Z",
  "targetDates": [
    "2025-09-04",
    "2025-09-03"
  ],
  "totalCount": 3,
  "announcements": [
    {
      "title": "함께 성장하는 K-방산 '25-2차 혁신기술·장비 소개회 개최",
      "link": "https://www.gntp.or.kr",
      "date": "2025-09-03",
      "site": "GNTP"
    },
    {
      "title": "경상남도, 중소기업 밀집지역 하반기 Stand-up 맞춤지원 공고 실시",
      "link": "https://www.gntp.or.kr",
      "date": "2025-09-03",
      "site": "GNTP"
    },
    {
      "title": "2025년 (재)경남테크노파크 인력(기간제) 채용 재공고 서류전형 합격자 공고(2025-295호 관련)",
      "link": "https://www.gntp.or.kr",
      "date": "2025-09-03",
      "site": "GNTP"
    }
  ]
}